LICENSE
MANIFEST.in
README.rst
pavement.py
requirements-dev.txt
requirements.txt
setup.py
tox.ini
btsprice/__init__.py
btsprice/bts_price_after_match.py
btsprice/exchanges.py
btsprice/feedapi.py
btsprice/feedprice.py
btsprice/main.py
btsprice/metadata.py
btsprice/misc.py
btsprice/sina.py
btsprice/task_exchanges.py
btsprice/task_pusher.py
btsprice/yahoo.py
btsprice.egg-info/PKG-INFO
btsprice.egg-info/SOURCES.txt
btsprice.egg-info/dependency_links.txt
btsprice.egg-info/entry_points.txt
btsprice.egg-info/not-zip-safe
btsprice.egg-info/requires.txt
btsprice.egg-info/top_level.txt
docs/Makefile
docs/make.bat
docs/source/README
docs/source/conf.py
docs/source/index.rst
docs/source/_static/.gitkeep
tests/test_main.py